LICENSE.txt
README.md
pyproject.toml
setup.cfg
setup.py
padsXiv/__init__.py
padsXiv.egg-info/PKG-INFO
padsXiv.egg-info/SOURCES.txt
padsXiv.egg-info/dependency_links.txt
padsXiv.egg-info/top_level.txt