Metadata-Version: 2.1
Name: padsXiv
Version: 0.1a0
Summary: A small package to get ads data from the facebook political ad library
Home-page: https://bitbucket.org/arman_noroozian/padsxiv/
Author: Arman Noroozian
Author-email: arman.noroozian@gmail.com
License: UNKNOWN
Project-URL: Bug Reports, https://bitbucket.org/arman_noroozian/padsxiv/issues
Project-URL: Source, https://bitbucket.org/arman_noroozian/padsxiv/
Keywords: ads,facebook
Platform: UNKNOWN
Classifier: Development Status :: 3 - Alpha
Classifier: Intended Audience :: Science/Research
Classifier: Topic :: Software Development :: Libraries :: Python Modules
Classifier: Topic :: Utilities
Classifier: License :: OSI Approved :: MIT License
Classifier: Programming Language :: Python :: 3
Classifier: Programming Language :: Python :: 3.6
Classifier: Programming Language :: Python :: 3.7
Classifier: Programming Language :: Python :: 3.8
Classifier: Programming Language :: Python :: 3.9
Requires-Python: >=3.6, <4
